[
  {
    "name" : "intent_names_username_extend",
    "keyphrases": ["mon nom est", "je m'appelle", "je suis", "voici"]
  },
  {
    "name": "intent_weather_extend",
    "keyphrases": ["quel temps fait-il", "quel temps fera-t-il", "météo", "pleuvoir", "pleut", "beau", "il va faire quel temps aujourd'hui", "est-ce qu'il pleut", "est-ce qu'il fait beau"]
  },
  {
    "name": "intent_names_ask",
    "keyphrases": ["quel est mon nom", "comment je m'appelle", "qui suis-je", "je suis qui", "tu me connais", "tu me reconnais", "qui je suis", "tu te souviens de moi"]
  },
  {
    "name": "intent_imperative_eyecolor",
    "keyphrases": ["couleur des yeux", "couleur des yeux", "changer la couleur", "yeux"]
  },
  {
    "name": "intent_character_age",
    "keyphrases": ["quel est ton âge", "quel âge as-tu", "tu es jeune", "tu es vieux"]
  },
  {
    "name": "intent_explore_start",
    "keyphrases": ["vas explorer", "explore", "explorer", "pars faire une promenade", "fais un tour", "pars explorer"]
  },
  {
    "name": "intent_system_charger",
    "keyphrases": ["rentre à la maison", "à la maison", "recharger", "trouve le chargeur", "aller en charge", "rentre à ta base"]
  },
  {
    "name": "intent_system_sleep",
    "keyphrases": ["va te coucher", "couché", "vas dormir", "dormir", "vas au lit", "lit", "bonne nuit", "dodo", "tu es fatigué"]
  },
  {
    "name": "intent_greeting_goodmorning",
    "keyphrases": ["jour", "matin", "après-midi"]
  },
  {
    "name": "intent_greeting_goodnight",
    "keyphrases": ["soir", "soirée"]
  },
  {
    "name": "intent_greeting_goodbye",
    "keyphrases": ["adieu", "au revoir", "à bientôt"]
  },
  {
    "name": "intent_seasonal_happynewyear",
    "keyphrases": ["fireworks", "bonne année"]
  },
  {
    "name": "intent_seasonal_happyholidays",
    "keyphrases": ["noël", "vacance", "joyeuses fêtes"]
  },
  {
    "name": "intent_amazon_signin",
    "keyphrases": ["entrez alexa", "inscrivez-toi sur alexa", "activez alexa"]
  },
  {
    "name": "intent_amazon_signin",
    "keyphrases": ["sortez d'alexa", "désactivez alexa"]
  },
  {
    "name": "intent_imperative_forward",
    "keyphrases": ["avance"]
  },
  {
    "name": "intent_imperative_turnaround",
    "keyphrases": ["tourne"]
  },
  {
    "name": "intent_imperative_turnleft",
    "keyphrases": ["tourne à gauche", "vas à gauche"]
  },
  {
    "name": "intent_imperative_turnright",
    "keyphrases": ["tourne à droite", "vas à droite"]
  },
  {
    "name": "intent_play_rollcube",
    "keyphrases": ["joue avec le cube", "cherche ton cube", "déplacez le cube"]
  },
  {
    "name": "intent_play_popawheelie",
    "keyphrases": ["sifflez"]
  },
  {
    "name": "intent_play_fistbump",
    "keyphrases": ["tapes m'en cinq", "check"]
  },
  {
    "name": "intent_play_blackjack",
    "keyphrases": ["vingt-un", "blackjack"]
  },
  {
    "name": "intent_imperative_affirmative",
    "keyphrases": ["oui", "bravo", "correct", "affirmatif", "vrai", "c'est juste"]
  },
  {
    "name": "intent_imperative_negative",
    "keyphrases": ["non", "pas", "mal", "false"]
  },
  {
    "name": "intent_photo_take_extend",
    "keyphrases": ["photo", "selfie", "image"]
  },
  {
    "name": "intent_imperative_praise",
    "keyphrases": ["bon", "gros", "mythique", "fort", "impressionnant", "balèze"]
  },
  {
    "name": "intent_imperative_abuse",
    "keyphrases": ["mal", "stupide", "ça ne va pas"]
  },
  {
    "name": "intent_imperative_apologize",
    "keyphrases": ["je suis désolé", "désolé"]
  },
  {
    "name": "intent_imperative_backup",
    "keyphrases": ["en arrière"]
  },
  {
    "name": "intent_imperative_volumedown",
    "keyphrases": ["abaisse le volume", "moins fort"]
  },
  {
    "name": "intent_imperative_volumeup",
    "keyphrases": ["augmente le volume", "plus fort"]
  },
  {
    "name": "intent_imperative_lookatme",
    "keyphrases": ["regarde-moi", "regarde moi", "regarde vers moi", "par ici", "hé ho"]
  },
  {
    "name": "intent_imperative_volumelevel_extend",
    "keyphrases": ["volume"]
  },
  {
    "name": "intent_imperative_shutup",
    "keyphrases": ["tais-toi", "silence", "ferme", "du calme"]
  },
  {
    "name": "intent_greeting_hello",
    "keyphrases": ["bonjour", "comment vas-tu", "bonjour", "bonne soirée", "bon après-midi", "hey", "salut"]
  },
  {
    "name": "intent_imperative_come",
    "keyphrases": ["viens ici", "viens à moi", "ici", "viens vers moi"]
  },
  {
    "name": "intent_imperative_love",
    "keyphrases": ["je t'aime", "mon amour"]
  },
  {
    "name": "intent_knowledge_promptquestion",
    "keyphrases": ["question"]
  },
  {
    "name": "intent_clock_checktimer",
    "keyphrases": ["vérifiez le chronomètre", "vérifiez la minuterie"]
  },
  {
    "name": "intent_global_stop_extend",
    "keyphrases": ["arrête le minuteur", "arrête le chronomètre"]
  },
  {
    "name": "intent_clock_settimer_extend",
    "keyphrases": ["démarre le minuteur", "démarre le chronomètre"]
  },
  {
    "name": "intent_clock_time",
    "keyphrases": ["quelle heure est-il", "as tu l'heure", "est-ce qu'il est tard"]
  },
  {
    "name": "intent_imperative_quiet",
    "keyphrases": ["assez", "stop", "arrêtes tes bêtises", "du calme"]
  },
  {
    "name": "intent_imperative_dance",
    "keyphrases": ["danse"]
  },
  {
    "name": "intent_play_pickupcube",
    "keyphrases": ["ramasse"]
  },
  {
    "name": "intent_imperative_fetchcube",
    "keyphrases": ["apporte le cube"]
  },
  {
    "name": "intent_imperative_findcube",
    "keyphrases": ["trouves le cube", "trouves ton cube"]
  },
  {
    "name": "intent_play_anytrick",
    "keyphrases": ["fais quelque chose", "étonnes moi", "invente quelque chose", "fais n'importe quoi"]
  },
  {
    "name": "intent_message_recordmessage_extend",
    "keyphrases": ["enregistrer", "magnéto"]
  },
  {
    "name": "intent_message_playmessage_extend",
    "keyphrases": ["reproduire le message", "lisez le message"]
  },
  {
    "name": "intent_blackjack_hit",
    "keyphrases": ["hit"]
  },
  {
    "name": "intent_blackjack_stand",
    "keyphrases": ["stop", "arrêtes toi"]
  },
  {
    "name": "intent_play_keepaway",
    "keyphrases": ["restez loin", "loin", "supprimé", "back"]
  }
]
